stringcase/__init__.py
stringcase_new-1.2.2.dist-info/licenses/LICENSE
stringcase_new-1.2.2.dist-info/WHEEL
stringcase_new-1.2.2.dist-info/METADATA
stringcase_new-1.2.2.dist-info/RECORD
