Metadata-Version: 2.4
Name: stringcase-new
Version: 1.2.2
Summary: String case converter.
Author-email: Taka Okunishi <okunishitaka.com@gmail.com>
Maintainer-email: Karl Knechtel <zahlman@proton.me>
License-Expression: MIT
License-File: LICENSE
Project-URL: bugs, https://github.com/zahlman/stringcase-new/issues
Project-URL: changelog, https://github.com/zahlman/stringcase-new/blob/master/changelog.md
Project-URL: homepage, https://github.com/zahlman/stringcase-new
